jwtools_langflow/__init__.py
jwtools_langflow/movie_toolkit.py
jwtools_langflow/wrapper/__init__.py
jwtools_langflow/wrapper/tmdb_wrapper.py
jwtools_langflow-0.1.3.dist-info/LICENSE
jwtools_langflow-0.1.3.dist-info/METADATA
jwtools_langflow-0.1.3.dist-info/WHEEL
jwtools_langflow-0.1.3.dist-info/top_level.txt
jwtools_langflow-0.1.3.dist-info/RECORD
